topsis/__init__.py
topsis/__main__.py
Topsis_Gautam_102203061-1.0.0.dist-info/LICENSE
Topsis_Gautam_102203061-1.0.0.dist-info/METADATA
Topsis_Gautam_102203061-1.0.0.dist-info/WHEEL
Topsis_Gautam_102203061-1.0.0.dist-info/entry_points.txt
Topsis_Gautam_102203061-1.0.0.dist-info/top_level.txt
Topsis_Gautam_102203061-1.0.0.dist-info/RECORD
