Metadata-Version: 2.2
Name: Topsis-Gautam-102203061
Version: 1.0.0
Summary: TOPSIS (Technique for Order of Preference by Similarity to Ideal Solution) is a multi-criteria decision-making method that ranks alternatives based on their closeness to the ideal solution.
Home-page: https://github.com/gautamdhw/Topsis-Gautam-102203061
Author: Gautam
Author-email: gautamdhawan910@gmail.com
License: MIT
Classifier: License :: OSI Approved :: MIT License
Classifier: Programming Language :: Python :: 3.6
Classifier: Programming Language :: Python :: 3.7
Classifier: Programming Language :: Python :: 3.8
License-File: LICENSE
Dynamic: author
Dynamic: author-email
Dynamic: classifier
Dynamic: description
Dynamic: description-content-type
Dynamic: home-page
Dynamic: license
Dynamic: summary
